hop/__init__.py
hop/__main__.py
hop/_version.py
hop/auth.py
hop/avro_utils.py
hop/cli.py
hop/configure.py
hop/http_scram.py
hop/io.py
hop/list_topics.py
hop/models.py
hop/publish.py
hop/robust_publisher.py
hop/subscribe.py
hop/version.py
hop/bson/LICENSE
hop/bson/LICENSE_APACHE
hop/bson/__init__.py
hop/bson/codec.py
hop/bson/network.py
hop/bson/objectid.py
hop/bson/py3compat.py
hop/bson/tz_util.py
hop/plugins/__init__.py
hop/utils/__init__.py
hop/utils/cli.py
hop_client-0.12.1.dist-info/licenses/LICENSE
hop_client-0.12.1.dist-info/licenses/hop/bson/LICENSE
hop_client-0.12.1.dist-info/licenses/hop/bson/LICENSE_APACHE
hop_client-0.12.1.dist-info/METADATA
hop_client-0.12.1.dist-info/WHEEL
hop_client-0.12.1.dist-info/entry_points.txt
hop_client-0.12.1.dist-info/top_level.txt
hop_client-0.12.1.dist-info/RECORD
