Metadata-Version: 2.4
Name: hop-client
Version: 0.12.1
Summary: A pub-sub client library for Multi-messenger Astrophysics
Author-email: Patrick Godwin <p@trick.dev>
License-Expression: BSD-3-Clause AND Apache-2.0
Project-URL: Homepage, https://github.com/scimma/hop-client
Project-URL: Documentation, https://hop-client.readthedocs.io
Project-URL: Issues, https://github.com/scimma/hop-client/issues
Classifier: Development Status :: 5 - Production/Stable
Classifier: Programming Language :: Python
Classifier: Programming Language :: Python :: 3
Classifier: Intended Audience :: Science/Research
Classifier: Intended Audience :: Developers
Classifier: Natural Language :: English
Classifier: Topic :: Scientific/Engineering
Classifier: Topic :: Scientific/Engineering :: Astronomy
Classifier: Topic :: Scientific/Engineering :: Physics
Classifier: Operating System :: POSIX
Classifier: Operating System :: Unix
Classifier: Operating System :: MacOS
Requires-Python: >=3.8
License-File: LICENSE
License-File: hop/bson/LICENSE
License-File: hop/bson/LICENSE_APACHE
Requires-Dist: adc-streaming>=2.6.0
Requires-Dist: fastavro>=1.4.0
Requires-Dist: requests
Requires-Dist: pluggy>=0.11
Requires-Dist: python-dateutil>=2.4.0
Requires-Dist: scramp
Requires-Dist: toml>=0.9.4
Requires-Dist: xmltodict>=0.9.0
Provides-Extra: dev
Requires-Dist: autopep8; extra == "dev"
Requires-Dist: build; extra == "dev"
Requires-Dist: flake8>=3.3.0; extra == "dev"
Requires-Dist: flake8-pyproject; extra == "dev"
Requires-Dist: pytest>=6.2.5; extra == "dev"
Requires-Dist: pytest-console-scripts; extra == "dev"
Requires-Dist: pytest-cov; extra == "dev"
Requires-Dist: pytest-runner; extra == "dev"
Requires-Dist: setuptools_scm; extra == "dev"
Requires-Dist: twine; extra == "dev"
Provides-Extra: docs
Requires-Dist: sphinx; extra == "docs"
Requires-Dist: sphinx_rtd_theme; extra == "docs"
Requires-Dist: sphinxcontrib-programoutput; extra == "docs"
Dynamic: license-file
